aiocrossref/__init__.py
aiocrossref/cli.py
aiocrossref/client.py
aiocrossref/exceptions.py
aiocrossref-0.3.0.dist-info/LICENSE
aiocrossref-0.3.0.dist-info/METADATA
aiocrossref-0.3.0.dist-info/WHEEL
aiocrossref-0.3.0.dist-info/entry_points.txt
aiocrossref-0.3.0.dist-info/top_level.txt
aiocrossref-0.3.0.dist-info/RECORD
