Metadata-Version: 2.1
Name: aiocrossref
Version: 0.3.0
Home-page: https://github.com/izihawa/aiocrossref
Author: Pasha Podolsky
License: MIT
Classifier: Topic :: Utilities
License-File: LICENSE
Requires-Dist: aiobaseclient (>=0.1.0)
Requires-Dist: fire (>=0.3.1)
Requires-Dist: izihawa-types (>=0.1.0)
